{
  "editor:swap-line-down": [
    {
      "modifiers": [
        "Alt",
        "Mod"
      ],
      "key": "ArrowDown"
    }
  ],
  "editor:swap-line-up": [
    {
      "modifiers": [
        "Alt",
        "Mod"
      ],
      "key": "ArrowUp"
    }
  ],
  "markdown:toggle-preview": [
    {
      "modifiers": [
        "Mod"
      ],
      "key": "."
    }
  ],
  "daily-notes": [
    {
      "modifiers": [
        "Mod"
      ],
      "key": "/"
    }
  ],
  "editor:toggle-comments": [],
  "app:toggle-left-sidebar": [
    {
      "modifiers": [
        "Mod",
        "Shift"
      ],
      "key": "-"
    }
  ],
  "app:toggle-right-sidebar": [
    {
      "modifiers": [
        "Mod",
        "Shift"
      ],
      "key": "="
    }
  ],
  "app:go-forward": [
    {
      "modifiers": [
        "Mod",
        "Shift"
      ],
      "key": "]"
    }
  ],
  "app:go-back": [
    {
      "modifiers": [
        "Mod",
        "Shift"
      ],
      "key": "["
    }
  ]
}